commonlibs/__init__.py
commonlibs/log.py
commonlibs/dicts/__init__.py
commonlibs/dicts/special.py
commonlibs/fileio/__init__.py
commonlibs/fileio/json.py
commonlibs/fileio/paths.py
commonlibs/logger/__init__.py
commonlibs/logger/logger.py
commonlibs/math/__init__.py
commonlibs/math/interpolation.py
commonlibs/math/vectors.py
commonlibs/strings/__init__.py
commonlibs/strings/strings.py
commonlibs-1.0.0.dist-info/licenses/LICENSE.txt
commonlibs-1.0.0.dist-info/METADATA
commonlibs-1.0.0.dist-info/WHEEL
commonlibs-1.0.0.dist-info/top_level.txt
commonlibs-1.0.0.dist-info/RECORD
