Metadata-Version: 2.4
Name: commonlibs
Version: 1.0.0
Summary: Libraries used by different packages
Home-page: https://github.com/airinnova/commonlibs
Author: Aaron Dettmann
Author-email: dettmann@kth.se
License: Apache License 2.0
Classifier: Programming Language :: Python :: 3.11
Classifier: License :: OSI Approved :: Apache Software License
Classifier: Operating System :: OS Independent
Classifier: Environment :: Console
Classifier: Intended Audience :: Developers
Classifier: Intended Audience :: Education
Classifier: Intended Audience :: Science/Research
Classifier: Topic :: Scientific/Engineering
Requires-Python: >=3.11.11
License-File: LICENSE.txt
Requires-Dist: numpy
Requires-Dist: schemadict
Dynamic: author
Dynamic: author-email
Dynamic: classifier
Dynamic: description
Dynamic: description-content-type
Dynamic: home-page
Dynamic: license
Dynamic: license-file
Dynamic: requires-dist
Dynamic: requires-python
Dynamic: summary
